MANIFEST.in
README.md
setup.cfg
setup.py
pyswf.egg-info/PKG-INFO
pyswf.egg-info/SOURCES.txt
pyswf.egg-info/dependency_links.txt
pyswf.egg-info/requires.txt
pyswf.egg-info/top_level.txt
swf/__init__.py
swf/actions.py
swf/consts.py
swf/data.py
swf/export.py
swf/filters.py
swf/geom.py
swf/movie.py
swf/sound.py
swf/stream.py
swf/tag.py
swf/utils.py