Metadata-Version: 1.1
Name: pyswf
Version: 1.5.3
Summary: SWF Parsing Utilities
Home-page: https://github.com/timknip/pyswf
Author: Tim Knip
Author-email: tim@floorplanner.com
License: MIT
Keywords: swf parser parsing decompile utilities
Platform: UNKNOWN
Classifier: Development Status :: 4 - Beta
Classifier: Topic :: Utilities
Classifier: License :: OSI Approved :: MIT License
